hdeeprm/__init__.py
hdeeprm/__meta__.py
hdeeprm/__xml__.py
hdeeprm/agent.py
hdeeprm/cmd.py
hdeeprm/environment.py
hdeeprm/manager.py
hdeeprm/resource.py
hdeeprm/util.py
hdeeprm/data/memory_types.json
hdeeprm/data/network_types.json
hdeeprm/data/node_types.json
hdeeprm/data/processor_types.json
hdeeprm/entrypoints/BaseWorkloadManager.py
hdeeprm/entrypoints/HDeepRMWorkloadManager.py
hdeeprm/entrypoints/__init__.py
hdeeprm-0.3.1b1.dist-info/LICENSE
hdeeprm-0.3.1b1.dist-info/METADATA
hdeeprm-0.3.1b1.dist-info/WHEEL
hdeeprm-0.3.1b1.dist-info/entry_points.txt
hdeeprm-0.3.1b1.dist-info/top_level.txt
hdeeprm-0.3.1b1.dist-info/RECORD
