Metadata-Version: 2.1
Name: hdeeprm
Version: 0.3.1b1
Summary: Evaluate Deep Reinforcement Learning policies for heterogeneous Workload Management
Home-page: https://github.com/RaMdsC/hdeeprm
Author: Adrián Herrera
Author-email: adr.her.arc.95@gmail.com
License: MIT
Keywords: deep reinforcement learning workload management job scheduling resource simulator framework heterogeneous cluster batsim
Platform: UNKNOWN
Classifier: Development Status :: 4 - Beta
Classifier: Intended Audience :: Science/Research
Classifier: License :: OSI Approved :: MIT License
Classifier: Natural Language :: English
Classifier: Programming Language :: Python :: 3.6
Classifier: Topic :: Scientific/Engineering :: Artificial Intelligence
Requires-Dist: defusedxml (>=0.5.0)
Requires-Dist: evalys (>=4.0.4)
Requires-Dist: gym (>=0.12.0)
Requires-Dist: lxml (>=4.3.2)
Requires-Dist: matplotlib (>=3.0.3)
Requires-Dist: numpy (>=1.16.2)
Requires-Dist: procset (>=1.0)
Requires-Dist: pybatsim (>=3.1.0)
Requires-Dist: torch (>=1.0.1.post2)
